Metadata-Version: 2.1
Name: jk-bincontainer
Version: 0.2021.10.30
Summary: This python module implements a container for data blocks.
Home-page: UNKNOWN
Author: Jürgen Knauth
Author-email: pubsrc@binary-overflow.de
License: Apache2
Keywords: binary,container
Platform: UNKNOWN
Classifier: Development Status :: 4 - Beta
Classifier: License :: OSI Approved :: Apache Software License
Classifier: Programming Language :: Python :: 3
